{"atlas":{"type":"msdf","distanceRange":8,"size":128,"width":1024,"height":1024,"yOrigin":"bottom"},"metrics":{"emSize":1,"lineHeight":1.14990234375,"ascender":0.9052734375,"descender":-0.2119140625,"underlineY":-0.142578125,"underlineThickness":0.0732421875},"glyphs":[{"unicode":32,"advance":0.24755859375},{"unicode":33,"advance":0.27783203125},{"unicode":34,"advance":0.35498046875},{"unicode":35,"advance":0.55615234375},{"unicode":36,"advance":0.55615234375},{"unicode":37,"advance":0.88916015625},{"unicode":38,"advance":0.6669921875},{"unicode":39,"advance":0.19091796875},{"unicode":40,"advance":1.63623046875,"planeBounds":{"left":-0.0341796875,"bottom":0.1162109375,"right":1.6845703125,"top":0.5380859375},"atlasBounds":{"left":502.5,"bottom":343.5,"right":722.5,"top":397.5}},{"unicode":41,"advance":0.7998046875,"planeBounds":{"left":-0.0439453125,"bottom":0.185546875,"right":0.8232421875,"top":0.482421875},"atlasBounds":{"left":260.5,"bottom":3.5,"right":371.5,"top":41.5}},{"unicode":42,"advance":0.38916015625},{"unicode":43,"advance":0.583984375},{"unicode":44,"advance":0.24755859375,"planeBounds":{"left":-0.041015625,"bottom":0.185546875,"right":0.287109375,"top":0.482421875},"atlasBounds":{"left":372.5,"bottom":3.5,"right":414.5,"top":41.5}},{"unicode":45,"advance":0.24755859375,"planeBounds":{"left":-0.041015625,"bottom":0.185546875,"right":0.287109375,"top":0.482421875},"atlasBounds":{"left":415.5,"bottom":3.5,"right":457.5,"top":41.5}},{"unicode":46,"advance":0.24755859375,"planeBounds":{"left":-0.041015625,"bottom":0.185546875,"right":0.287109375,"top":0.482421875},"atlasBounds":{"left":955.5,"bottom":877.5,"right":997.5,"top":915.5}},{"unicode":47,"advance":0.27783203125},{"unicode":48,"advance":0.55615234375},{"unicode":49,"advance":0.55615234375},{"unicode":50,"advance":0.55615234375},{"unicode":51,"advance":0.55615234375},{"unicode":52,"advance":0.55615234375},{"unicode":53,"advance":0.55615234375},{"unicode":54,"advance":0.55615234375},{"unicode":55,"advance":0.55615234375},{"unicode":56,"advance":0.55615234375},{"unicode":57,"advance":0.55615234375},{"unicode":58,"advance":0.27783203125},{"unicode":59,"advance":0.27783203125},{"unicode":60,"advance":1.63623046875,"planeBounds":{"left":-0.0341796875,"bottom":0.1162109375,"right":1.6845703125,"top":0.5380859375},"atlasBounds":{"left":502.5,"bottom":288.5,"right":722.5,"top":342.5}},{"unicode":61,"advance":0.583984375},{"unicode":62,"advance":0.7998046875,"planeBounds":{"left":-0.0439453125,"bottom":0.185546875,"right":0.8232421875,"top":0.482421875},"atlasBounds":{"left":735.5,"bottom":868.5,"right":846.5,"top":906.5}},{"unicode":63,"advance":0.55615234375},{"unicode":64,"advance":1.01513671875},{"unicode":65,"advance":1.70703125,"planeBounds":{"left":-0.0322265625,"bottom":-0.044921875,"right":1.7958984375,"top":0.861328125},"atlasBounds":{"left":260.5,"bottom":592.5,"right":494.5,"top":708.5}},{"unicode":66,"advance":1.73828125,"planeBounds":{"left":-0.033203125,"bottom":-0.04296875,"right":1.787109375,"top":0.71484375},"atlasBounds":{"left":260.5,"bottom":279.5,"right":493.5,"top":376.5}},{"unicode":67,"advance":1.6162109375,"planeBounds":{"left":-0.0341796875,"bottom":-0.0390625,"right":1.7236328125,"top":0.7109375},"atlasBounds":{"left":502.5,"bottom":493.5,"right":727.5,"top":589.5}},{"unicode":68,"advance":1.810546875,"planeBounds":{"left":-0.0341796875,"bottom":-0.046875,"right":1.8642578125,"top":0.7109375},"atlasBounds":{"left":0.5,"bottom":449.5,"right":243.5,"top":546.5}},{"unicode":69,"advance":1.7783203125,"planeBounds":{"left":-0.0322265625,"bottom":-0.0517578125,"right":1.8271484375,"top":0.7138671875},"atlasBounds":{"left":260.5,"bottom":827.5,"right":498.5,"top":925.5}},{"unicode":70,"advance":1.7265625,"planeBounds":{"left":-0.0322265625,"bottom":-0.2080078125,"right":1.7802734375,"top":0.7138671875},"atlasBounds":{"left":260.5,"bottom":42.5,"right":492.5,"top":160.5}},{"unicode":71,"advance":1.80322265625,"planeBounds":{"left":-0.0322265625,"bottom":-0.044921875,"right":1.8505859375,"top":0.712890625},"atlasBounds":{"left":260.5,"bottom":926.5,"right":501.5,"top":1023.5}},{"unicode":72,"advance":1.7783203125,"planeBounds":{"left":-0.0322265625,"bottom":-0.2197265625,"right":1.8271484375,"top":0.7099609375},"atlasBounds":{"left":0.5,"bottom":0.5,"right":238.5,"top":119.5}},{"unicode":73,"advance":1.630859375,"planeBounds":{"left":-0.0341796875,"bottom":-0.044921875,"right":1.6767578125,"top":0.720703125},"atlasBounds":{"left":502.5,"bottom":79.5,"right":721.5,"top":177.5}},{"unicode":74,"advance":1.62890625,"planeBounds":{"left":-0.0341796875,"bottom":-0.04296875,"right":1.6767578125,"top":0.86328125},"atlasBounds":{"left":735.5,"bottom":907.5,"right":954.5,"top":1023.5}},{"unicode":75,"advance":1.62646484375,"planeBounds":{"left":-0.0322265625,"bottom":-0.2001953125,"right":1.8271484375,"top":0.7138671875},"atlasBounds":{"left":260.5,"bottom":709.5,"right":498.5,"top":826.5}},{"unicode":76,"advance":1.71044921875,"planeBounds":{"left":-0.0322265625,"bottom":-0.0478515625,"right":1.7802734375,"top":0.7099609375},"atlasBounds":{"left":502.5,"bottom":926.5,"right":734.5,"top":1023.5}},{"unicode":77,"advance":1.8916015625,"planeBounds":{"left":-0.033203125,"bottom":-0.2314453125,"right":1.943359375,"top":0.7138671875},"atlasBounds":{"left":0.5,"bottom":784.5,"right":253.5,"top":905.5}},{"unicode":78,"advance":1.74755859375,"planeBounds":{"left":-0.03125,"bottom":-0.2001953125,"right":1.7890625,"top":0.7138671875},"atlasBounds":{"left":260.5,"bottom":161.5,"right":493.5,"top":278.5}},{"unicode":79,"advance":1.81982421875,"planeBounds":{"left":-0.0322265625,"bottom":-0.0458984375,"right":1.8662109375,"top":0.7119140625},"atlasBounds":{"left":0.5,"bottom":351.5,"right":243.5,"top":448.5}},{"unicode":80,"advance":1.74755859375,"planeBounds":{"left":-0.0322265625,"bottom":-0.0439453125,"right":1.7958984375,"top":0.7138671875},"atlasBounds":{"left":260.5,"bottom":494.5,"right":494.5,"top":591.5}},{"unicode":81,"advance":1.81591796875,"planeBounds":{"left":-0.0322265625,"bottom":-0.1484375,"right":1.8662109375,"top":0.7109375},"atlasBounds":{"left":0.5,"bottom":240.5,"right":243.5,"top":350.5}},{"unicode":82,"advance":1.73876953125,"planeBounds":{"left":-0.03125,"bottom":-0.21875,"right":1.8671875,"top":0.7109375},"atlasBounds":{"left":0.5,"bottom":120.5,"right":243.5,"top":239.5}},{"unicode":83,"advance":1.736328125,"planeBounds":{"left":-0.03125,"bottom":-0.04931640625,"right":1.78125,"top":0.71630859375},"atlasBounds":{"left":502.5,"bottom":827.5,"right":734.5,"top":925.5}},{"unicode":84,"advance":1.734375,"planeBounds":{"left":-0.03125,"bottom":-0.2158203125,"right":1.78125,"top":0.7138671875},"atlasBounds":{"left":502.5,"bottom":707.5,"right":734.5,"top":826.5}},{"unicode":85,"advance":1.736328125,"planeBounds":{"left":-0.03125,"bottom":-0.046875,"right":1.78125,"top":0.859375},"atlasBounds":{"left":502.5,"bottom":590.5,"right":734.5,"top":706.5}},{"unicode":86,"advance":1.74169921875,"planeBounds":{"left":-0.0322265625,"bottom":-0.212890625,"right":1.7958984375,"top":0.693359375},"atlasBounds":{"left":260.5,"bottom":377.5,"right":494.5,"top":493.5}},{"unicode":87,"advance":1.88818359375,"planeBounds":{"left":-0.0322265625,"bottom":-0.0458984375,"right":1.9365234375,"top":0.8681640625},"atlasBounds":{"left":0.5,"bottom":666.5,"right":252.5,"top":783.5}},{"unicode":88,"advance":1.81494140625,"planeBounds":{"left":-0.03125,"bottom":-0.0439453125,"right":1.9921875,"top":0.8701171875},"atlasBounds":{"left":0.5,"bottom":906.5,"right":259.5,"top":1023.5}},{"unicode":89,"advance":1.7802734375,"planeBounds":{"left":-0.0322265625,"bottom":-0.2177734375,"right":1.9365234375,"top":0.7041015625},"atlasBounds":{"left":0.5,"bottom":547.5,"right":252.5,"top":665.5}},{"unicode":90,"advance":1.6494140625,"planeBounds":{"left":-0.0322265625,"bottom":-0.04296875,"right":1.7177734375,"top":0.69140625},"atlasBounds":{"left":502.5,"bottom":398.5,"right":726.5,"top":492.5}},{"unicode":91,"advance":1.63623046875,"planeBounds":{"left":-0.0341796875,"bottom":0.1162109375,"right":1.6845703125,"top":0.5380859375},"atlasBounds":{"left":502.5,"bottom":178.5,"right":722.5,"top":232.5}},{"unicode":92,"advance":0.27783203125},{"unicode":93,"advance":0.7998046875,"planeBounds":{"left":-0.0439453125,"bottom":0.185546875,"right":0.8232421875,"top":0.482421875},"atlasBounds":{"left":735.5,"bottom":829.5,"right":846.5,"top":867.5}},{"unicode":94,"advance":0.46923828125},{"unicode":95,"advance":0.24755859375,"planeBounds":{"left":-0.041015625,"bottom":0.185546875,"right":0.287109375,"top":0.482421875},"atlasBounds":{"left":955.5,"bottom":838.5,"right":997.5,"top":876.5}},{"unicode":96,"advance":0.3330078125},{"unicode":97,"advance":0.52197265625,"planeBounds":{"left":-0.0478515625,"bottom":0.0693359375,"right":0.5615234375,"top":0.7099609375},"atlasBounds":{"left":847.5,"bottom":257.5,"right":925.5,"top":339.5}},{"unicode":98,"advance":0.4462890625,"planeBounds":{"left":-0.04296875,"bottom":0.0703125,"right":0.48828125,"top":0.6015625},"atlasBounds":{"left":580.5,"bottom":10.5,"right":648.5,"top":78.5}},{"unicode":99,"advance":0.42041015625,"planeBounds":{"left":-0.04296875,"bottom":0.06640625,"right":0.46484375,"top":0.59765625},"atlasBounds":{"left":955.5,"bottom":955.5,"right":1020.5,"top":1023.5}},{"unicode":100,"advance":0.46875,"planeBounds":{"left":-0.0380859375,"bottom":0.0673828125,"right":0.5087890625,"top":0.5986328125},"atlasBounds":{"left":735.5,"bottom":32.5,"right":805.5,"top":100.5}},{"unicode":101,"advance":0.46435546875,"planeBounds":{"left":-0.04296875,"bottom":0.072265625,"right":0.50390625,"top":0.595703125},"atlasBounds":{"left":735.5,"bottom":419.5,"right":805.5,"top":486.5}},{"unicode":102,"advance":0.45166015625,"planeBounds":{"left":-0.04296875,"bottom":-0.052734375,"right":0.50390625,"top":0.595703125},"atlasBounds":{"left":735.5,"bottom":252.5,"right":805.5,"top":335.5}},{"unicode":103,"advance":0.5263671875,"planeBounds":{"left":-0.04296875,"bottom":0.0673828125,"right":0.56640625,"top":0.5986328125},"atlasBounds":{"left":847.5,"bottom":340.5,"right":925.5,"top":408.5}},{"unicode":104,"advance":0.46533203125,"planeBounds":{"left":-0.04296875,"bottom":-0.0458984375,"right":0.50390625,"top":0.5947265625},"atlasBounds":{"left":735.5,"bottom":336.5,"right":805.5,"top":418.5}},{"unicode":105,"advance":0.2294921875,"planeBounds":{"left":-0.0439453125,"bottom":0.07275390625,"right":0.2763671875,"top":0.59619140625},"atlasBounds":{"left":955.5,"bottom":770.5,"right":996.5,"top":837.5}},{"unicode":106,"advance":0.45556640625,"planeBounds":{"left":-0.04296875,"bottom":0.0712890625,"right":0.50390625,"top":0.7119140625},"atlasBounds":{"left":735.5,"bottom":101.5,"right":805.5,"top":183.5}},{"unicode":107,"advance":0.45703125,"planeBounds":{"left":-0.041015625,"bottom":-0.0439453125,"right":0.529296875,"top":0.5966796875},"atlasBounds":{"left":735.5,"bottom":556.5,"right":808.5,"top":638.5}},{"unicode":108,"advance":0.45166015625,"planeBounds":{"left":-0.04296875,"bottom":0.072265625,"right":0.50390625,"top":0.595703125},"atlasBounds":{"left":735.5,"bottom":184.5,"right":805.5,"top":251.5}},{"unicode":109,"advance":0.541015625,"planeBounds":{"left":-0.04296875,"bottom":-0.044921875,"right":0.59765625,"top":0.595703125},"atlasBounds":{"left":847.5,"bottom":575.5,"right":929.5,"top":657.5}},{"unicode":110,"advance":0.45556640625,"planeBounds":{"left":-0.0439453125,"bottom":-0.0419921875,"right":0.5341796875,"top":0.5986328125},"atlasBounds":{"left":735.5,"bottom":639.5,"right":809.5,"top":721.5}},{"unicode":111,"advance":0.48876953125,"planeBounds":{"left":-0.04296875,"bottom":0.072265625,"right":0.53515625,"top":0.595703125},"atlasBounds":{"left":735.5,"bottom":722.5,"right":809.5,"top":789.5}},{"unicode":112,"advance":0.47412109375,"planeBounds":{"left":-0.0439453125,"bottom":0.0673828125,"right":0.5263671875,"top":0.5986328125},"atlasBounds":{"left":735.5,"bottom":487.5,"right":808.5,"top":555.5}},{"unicode":113,"advance":0.50341796875,"planeBounds":{"left":-0.0439453125,"bottom":-0.0107421875,"right":0.5576171875,"top":0.5908203125},"atlasBounds":{"left":502.5,"bottom":1.5,"right":579.5,"top":78.5}},{"unicode":114,"advance":0.50732421875,"planeBounds":{"left":-0.0419921875,"bottom":-0.044921875,"right":0.5751953125,"top":0.595703125},"atlasBounds":{"left":847.5,"bottom":409.5,"right":926.5,"top":491.5}},{"unicode":115,"advance":0.4775390625,"planeBounds":{"left":-0.0439453125,"bottom":0.06640625,"right":0.5419921875,"top":0.59765625},"atlasBounds":{"left":847.5,"bottom":22.5,"right":922.5,"top":90.5}},{"unicode":116,"advance":0.48876953125,"planeBounds":{"left":-0.0439453125,"bottom":-0.046875,"right":0.5419921875,"top":0.59375},"atlasBounds":{"left":847.5,"bottom":91.5,"right":922.5,"top":173.5}},{"unicode":117,"advance":0.50341796875,"planeBounds":{"left":-0.04296875,"bottom":0.0712890625,"right":0.55078125,"top":0.7119140625},"atlasBounds":{"left":847.5,"bottom":174.5,"right":923.5,"top":256.5}},{"unicode":118,"advance":0.5107421875,"planeBounds":{"left":-0.060546875,"bottom":-0.044921875,"right":0.556640625,"top":0.595703125},"atlasBounds":{"left":847.5,"bottom":492.5,"right":926.5,"top":574.5}},{"unicode":119,"advance":0.5810546875,"planeBounds":{"left":-0.048828125,"bottom":0.072265625,"right":0.630859375,"top":0.712890625},"atlasBounds":{"left":847.5,"bottom":658.5,"right":934.5,"top":740.5}},{"unicode":120,"advance":0.57763671875,"planeBounds":{"left":-0.0458984375,"bottom":0.0712890625,"right":0.6494140625,"top":0.7119140625},"atlasBounds":{"left":847.5,"bottom":824.5,"right":936.5,"top":906.5}},{"unicode":121,"advance":0.55517578125,"planeBounds":{"left":-0.06640625,"bottom":-0.0439453125,"right":0.62109375,"top":0.5966796875},"atlasBounds":{"left":847.5,"bottom":741.5,"right":935.5,"top":823.5}},{"unicode":122,"advance":0.462890625,"planeBounds":{"left":-0.0439453125,"bottom":0.072265625,"right":0.5185546875,"top":0.595703125},"atlasBounds":{"left":649.5,"bottom":11.5,"right":721.5,"top":78.5}},{"unicode":123,"advance":1.63623046875,"planeBounds":{"left":-0.0341796875,"bottom":0.1162109375,"right":1.6845703125,"top":0.5380859375},"atlasBounds":{"left":502.5,"bottom":233.5,"right":722.5,"top":287.5}},{"unicode":124,"advance":0.259765625},{"unicode":125,"advance":0.7998046875,"planeBounds":{"left":-0.0439453125,"bottom":0.185546875,"right":0.8232421875,"top":0.482421875},"atlasBounds":{"left":735.5,"bottom":790.5,"right":846.5,"top":828.5}},{"unicode":126,"advance":0.583984375},{"unicode":160,"advance":0.24755859375},{"unicode":161,"advance":0.3330078125},{"unicode":162,"advance":0.55615234375},{"unicode":163,"advance":0.55615234375},{"unicode":164,"advance":0.55615234375},{"unicode":165,"advance":0.55615234375},{"unicode":166,"advance":0.259765625},{"unicode":167,"advance":0.55615234375},{"unicode":168,"advance":0.3330078125},{"unicode":169,"advance":0.73681640625},{"unicode":170,"advance":0.3701171875},{"unicode":171,"advance":0.55615234375},{"unicode":172,"advance":0.583984375},{"unicode":173,"advance":0.24755859375,"planeBounds":{"left":-0.041015625,"bottom":0.185546875,"right":0.287109375,"top":0.482421875},"atlasBounds":{"left":955.5,"bottom":916.5,"right":997.5,"top":954.5}},{"unicode":174,"advance":0.73681640625},{"unicode":175,"advance":0.55224609375},{"unicode":176,"advance":0.39990234375},{"unicode":177,"advance":0.548828125},{"unicode":178,"advance":0.3330078125},{"unicode":179,"advance":0.3330078125},{"unicode":180,"advance":0.3330078125},{"unicode":181,"advance":0.576171875},{"unicode":182,"advance":0.537109375},{"unicode":183,"advance":0.27783203125},{"unicode":184,"advance":0.3330078125},{"unicode":185,"advance":0.3330078125},{"unicode":186,"advance":0.365234375},{"unicode":187,"advance":0.55615234375},{"unicode":188,"advance":0.833984375},{"unicode":189,"advance":0.833984375},{"unicode":190,"advance":0.833984375},{"unicode":191,"advance":0.61083984375},{"unicode":192,"advance":0.6669921875},{"unicode":193,"advance":0.6669921875},{"unicode":194,"advance":0.6669921875},{"unicode":195,"advance":0.6669921875},{"unicode":196,"advance":0.6669921875},{"unicode":197,"advance":0.6669921875},{"unicode":198,"advance":1},{"unicode":199,"advance":0.72216796875},{"unicode":200,"advance":0.6669921875},{"unicode":201,"advance":0.6669921875},{"unicode":202,"advance":0.6669921875},{"unicode":203,"advance":0.6669921875},{"unicode":204,"advance":0.27783203125},{"unicode":205,"advance":0.27783203125},{"unicode":206,"advance":0.27783203125},{"unicode":207,"advance":0.27783203125},{"unicode":208,"advance":0.72216796875},{"unicode":209,"advance":0.72216796875},{"unicode":210,"advance":0.77783203125},{"unicode":211,"advance":0.77783203125},{"unicode":212,"advance":0.77783203125},{"unicode":213,"advance":0.77783203125},{"unicode":214,"advance":0.77783203125},{"unicode":215,"advance":0.583984375},{"unicode":216,"advance":0.77783203125},{"unicode":217,"advance":0.72216796875},{"unicode":218,"advance":0.72216796875},{"unicode":219,"advance":0.72216796875},{"unicode":220,"advance":0.72216796875},{"unicode":221,"advance":0.6669921875},{"unicode":222,"advance":0.6669921875},{"unicode":223,"advance":0.61083984375},{"unicode":224,"advance":0.55615234375},{"unicode":225,"advance":0.55615234375},{"unicode":226,"advance":0.55615234375},{"unicode":227,"advance":0.55615234375},{"unicode":228,"advance":0.55615234375},{"unicode":229,"advance":0.55615234375},{"unicode":230,"advance":0.88916015625},{"unicode":231,"advance":0.5},{"unicode":232,"advance":0.55615234375},{"unicode":233,"advance":0.55615234375},{"unicode":234,"advance":0.55615234375},{"unicode":235,"advance":0.55615234375},{"unicode":236,"advance":0.27783203125},{"unicode":237,"advance":0.27783203125},{"unicode":238,"advance":0.27783203125},{"unicode":239,"advance":0.27783203125},{"unicode":240,"advance":0.55615234375},{"unicode":241,"advance":0.55615234375},{"unicode":242,"advance":0.55615234375},{"unicode":243,"advance":0.55615234375},{"unicode":244,"advance":0.55615234375},{"unicode":245,"advance":0.55615234375},{"unicode":246,"advance":0.55615234375},{"unicode":247,"advance":0.548828125},{"unicode":248,"advance":0.61083984375},{"unicode":249,"advance":0.55615234375},{"unicode":250,"advance":0.55615234375},{"unicode":251,"advance":0.55615234375},{"unicode":252,"advance":0.55615234375},{"unicode":253,"advance":0.5},{"unicode":254,"advance":0.55615234375},{"unicode":255,"advance":0.5}],"kerning":[]}
